reddcolors/__init__.py
reddcolors-0.1.0.dist-info/LICENSE
reddcolors-0.1.0.dist-info/METADATA
reddcolors-0.1.0.dist-info/WHEEL
reddcolors-0.1.0.dist-info/top_level.txt
reddcolors-0.1.0.dist-info/RECORD
