Metadata-Version: 2.1
Name: reddcolors
Version: 0.1.0
Summary: A very simple library for color management alongside jupyterthemes.
Author: ReddTea
Author-email: redd@tea.com
Classifier: Programming Language :: Python :: 3
Classifier: License :: OSI Approved :: MIT License
Classifier: Operating System :: OS Independent
Requires-Python: >=3.6
License-File: LICENSE
Requires-Dist: matplotlib (>=3.5.1)
Requires-Dist: jupyterthemes
